LICENSE
MANIFEST.in
README.md
VERSION
pyproject.toml
requirements.txt
setup.py
aequitas/__init__.py
aequitas/detection/__init__.py
aequitas/detection/descriptive_stats.py
aequitas/detection/metrics.py
aequitas/engine/__init__.py
aequitas/mitigation/__init__.py
aequitas/mitigation/data.py
aequitas/mitigation/models.py
aequitas/tools/__init__.py
aequitas/tools/data_manip.py
aequitas_lib.egg-info/PKG-INFO
aequitas_lib.egg-info/SOURCES.txt
aequitas_lib.egg-info/dependency_links.txt
aequitas_lib.egg-info/not-zip-safe
aequitas_lib.egg-info/requires.txt
aequitas_lib.egg-info/top_level.txt