Metadata-Version: 2.1
Name: aequitas-lib
Version: 1.0.0
Summary: Core library of the Aequitas project
Home-page: https://github.com/aequitas-aod/aequitas-lib
Author: Panagiotis Kyziropoulos
Author-email: panagiotis.kyziropoulos@ucc.ie
License: Apache 2.0 License
Project-URL: Bug Reports, https://github.com/aequitas-aod/aequitas-lib/issues
Project-URL: Source, https://github.com/aequitas-aod/aequitas-lib
Keywords: aeuitas,horizon2020,xai,bias
Platform: Independant
Classifier: Development Status :: 3 - Alpha
Classifier: Intended Audience :: Developers
Classifier: Topic :: Software Development :: Libraries
Classifier: Topic :: Scientific/Engineering :: Artificial Intelligence
Classifier: License :: OSI Approved :: Apache Software License
Classifier: Programming Language :: Python :: 3
Classifier: Programming Language :: Python :: 3 :: Only
Requires-Python: >=3.10.5
License-File: LICENSE
Requires-Dist: numpy>=1.26.0
Requires-Dist: scipy>=1.11.3
Requires-Dist: pandas>=2.0.3
Requires-Dist: scikit-learn>=1.2.2
